aiocypher/__init__.py
aiocypher/_version.py
aiocypher/config.py
aiocypher/empty.py
aiocypher/py.typed
aiocypher/aioagensgraph/__init__.py
aiocypher/aioagensgraph/driver.py
aiocypher/aioagensgraph/graph.py
aiocypher/aioagensgraph/node.py
aiocypher/aioagensgraph/py.typed
aiocypher/aioagensgraph/record.py
aiocypher/aioagensgraph/result.py
aiocypher/aioagensgraph/session.py
aiocypher/aioagensgraph/transaction.py
aiocypher/aioneo4j/__init__.py
aiocypher/aioneo4j/driver.py
aiocypher/aioneo4j/graph.py
aiocypher/aioneo4j/py.typed
aiocypher/aioneo4j/record.py
aiocypher/aioneo4j/result.py
aiocypher/aioneo4j/session.py
aiocypher/aioneo4j/transaction.py
aiocypher/interface/__init__.py
aiocypher/interface/driver.py
aiocypher/interface/exceptions.py
aiocypher/interface/graph.py
aiocypher/interface/node.py
aiocypher/interface/py.typed
aiocypher/interface/record.py
aiocypher/interface/relationship.py
aiocypher/interface/result.py
aiocypher/interface/session.py
aiocypher/interface/transaction.py
aiocypher/internal/__init__.py
aiocypher/internal/abc.py
aiocypher/internal/py.typed
aiocypher-0.1.4.dist-info/COPYING
aiocypher-0.1.4.dist-info/LICENSE.md
aiocypher-0.1.4.dist-info/METADATA
aiocypher-0.1.4.dist-info/WHEEL
aiocypher-0.1.4.dist-info/top_level.txt
aiocypher-0.1.4.dist-info/RECORD
